lead_perfection/__init__.py
lead_perfection/canvass.py
lead_perfection/client.py
lead_perfection/custom.py
lead_perfection/customers.py
lead_perfection/downloads.py
lead_perfection/file.py
lead_perfection/installer.py
lead_perfection/leads.py
lead_perfection/menu.py
lead_perfection/sales.py
lead_perfection/utils.py
lead_perfection-0.3.dist-info/METADATA
lead_perfection-0.3.dist-info/WHEEL
lead_perfection-0.3.dist-info/top_level.txt
lead_perfection-0.3.dist-info/RECORD
