Metadata-Version: 2.1
Name: lead-perfection
Version: 0.3
Summary: A Python library takes the LeadPerfection API methods and packages them in an easy to use format
Home-page: https://github.com/Tyler-Heist/lead-perfection
Author: Tyler Heist
Author-email: 
Maintainer: Tyler Heist
Project-URL: Homepage, https://github.com/Tyler-Heist/lead-perfection
Keywords: lead perfection,lp
Requires-Dist: requests
